<?xml version="1.0" encoding="UTF-8"?>
<!--
Created with Funkin Packer v0.1.3 https://neeeoo.github.io/funkin-packer/
-->
<TextureAtlas imagePath="freeplaynightmare.png" width="633" height="218" spritePadding="3" borderPadding="1">
	<SubTexture name="idle0000" x="425" y="75" width="207" height="69" frameX="0" frameY="0" frameWidth="209" frameHeight="72"/>
	<SubTexture name="idle0001" x="213" y="1" width="208" height="71" frameX="0" frameY="0" frameWidth="209" frameHeight="72"/>
	<SubTexture name="idle0002" x="425" y="147" width="207" height="69" frameX="0" frameY="0" frameWidth="209" frameHeight="72"/>
	<SubTexture name="idle0003" x="424" y="1" width="208" height="71" frameX="0" frameY="0" frameWidth="209" frameHeight="72"/>
	<SubTexture name="idle0004" x="425" y="75" width="207" height="69" frameX="0" frameY="0" frameWidth="209" frameHeight="72"/>
	<SubTexture name="idle0005" x="1" y="148" width="207" height="69" frameX="0" frameY="0" frameWidth="209" frameHeight="72"/>
	<SubTexture name="idle0006" x="1" y="75" width="209" height="70" frameX="0" frameY="0" frameWidth="209" frameHeight="72"/>
	<SubTexture name="idle0007" x="425" y="75" width="207" height="69" frameX="0" frameY="0" frameWidth="209" frameHeight="72"/>
	<SubTexture name="idle0008" x="425" y="75" width="207" height="69" frameX="0" frameY="0" frameWidth="209" frameHeight="72"/>
	<SubTexture name="idle0009" x="213" y="1" width="208" height="71" frameX="0" frameY="0" frameWidth="209" frameHeight="72"/>
	<SubTexture name="idle0010" x="425" y="147" width="207" height="69" frameX="0" frameY="0" frameWidth="209" frameHeight="72"/>
	<SubTexture name="idle0011" x="424" y="1" width="208" height="71" frameX="0" frameY="0" frameWidth="209" frameHeight="72"/>
	<SubTexture name="idle0012" x="425" y="75" width="207" height="69" frameX="0" frameY="0" frameWidth="209" frameHeight="72"/>
	<SubTexture name="idle0013" x="1" y="148" width="207" height="69" frameX="0" frameY="0" frameWidth="209" frameHeight="72"/>
	<SubTexture name="idle0014" x="1" y="75" width="209" height="70" frameX="0" frameY="0" frameWidth="209" frameHeight="72"/>
	<SubTexture name="idle0015" x="211" y="148" width="207" height="69" frameX="0" frameY="0" frameWidth="209" frameHeight="72"/>
	<SubTexture name="idle0016" x="424" y="1" width="208" height="71" frameX="0" frameY="0" frameWidth="209" frameHeight="72"/>
	<SubTexture name="idle0017" x="1" y="148" width="207" height="69" frameX="0" frameY="0" frameWidth="209" frameHeight="72"/>
	<SubTexture name="idle0018" x="425" y="147" width="207" height="69" frameX="0" frameY="0" frameWidth="209" frameHeight="72"/>
	<SubTexture name="idle0019" x="213" y="75" width="209" height="70" frameX="0" frameY="0" frameWidth="209" frameHeight="72"/>
	<SubTexture name="idle0020" x="425" y="75" width="207" height="69" frameX="0" frameY="0" frameWidth="209" frameHeight="72"/>
	<SubTexture name="idle0021" x="1" y="148" width="207" height="69" frameX="0" frameY="0" frameWidth="209" frameHeight="72"/>
	<SubTexture name="idle0022" x="1" y="1" width="209" height="71" frameX="0" frameY="0" frameWidth="209" frameHeight="72"/>
	<SubTexture name="idle0023" x="425" y="75" width="207" height="69" frameX="0" frameY="0" frameWidth="209" frameHeight="72"/>
	<SubTexture name="idle0024" x="424" y="1" width="208" height="71" frameX="0" frameY="0" frameWidth="209" frameHeight="72"/>
</TextureAtlas>