<?xml version="1.0" encoding="UTF-8"?>
<!--
Created with Funkin Packer v0.1.3 https://neeeoo.github.io/funkin-packer/
-->
<TextureAtlas imagePath="freeplayCapsule.png" width="1139" height="1016" spritePadding="3" borderPadding="1">
	<SubTexture name="mp3 capsule w backing NOT SELECTED0001" x="1" y="761" width="557" height="125" frameX="-37" frameY="-7" frameWidth="602" frameHeight="132"/>
	<SubTexture name="mp3 capsule w backing NOT SELECTED0002" x="561" y="761" width="557" height="125" frameX="-37" frameY="-7" frameWidth="602" frameHeight="132"/>
	<SubTexture name="mp3 capsule w backing NOT SELECTED0003" x="1" y="889" width="556" height="126" frameX="-38" frameY="-6" frameWidth="602" frameHeight="132"/>
	<SubTexture name="mp3 capsule w backing NOT SELECTED0004" x="560" y="889" width="556" height="126" frameX="-38" frameY="-6" frameWidth="602" frameHeight="132"/>
	<SubTexture name="mp3 capsule w backing NOT SELECTED0005" x="575" y="1" width="563" height="120" frameX="-31" frameY="-12" frameWidth="602" frameHeight="132"/>
	<SubTexture name="mp3 capsule w backing NOT SELECTED0006" x="575" y="124" width="563" height="120" frameX="-31" frameY="-12" frameWidth="602" frameHeight="132"/>
	<SubTexture name="mp3 capsule w backing NOT SELECTED0007" x="1" y="635" width="559" height="123" frameX="-35" frameY="-9" frameWidth="602" frameHeight="132"/>
	<SubTexture name="mp3 capsule w backing NOT SELECTED0008" x="563" y="635" width="559" height="123" frameX="-35" frameY="-9" frameWidth="602" frameHeight="132"/>
	<SubTexture name="mp3 capsule w backing0001" x="575" y="247" width="562" height="126" frameX="-37" frameY="-6" frameWidth="612" frameHeight="132"/>
	<SubTexture name="mp3 capsule w backing0002" x="568" y="376" width="562" height="126" frameX="-37" frameY="-6" frameWidth="612" frameHeight="132"/>
	<SubTexture name="mp3 capsule w backing0003" x="1" y="505" width="560" height="127" frameX="-39" frameY="-5" frameWidth="612" frameHeight="132"/>
	<SubTexture name="mp3 capsule w backing0004" x="564" y="505" width="560" height="127" frameX="-39" frameY="-5" frameWidth="612" frameHeight="132"/>
	<SubTexture name="mp3 capsule w backing0005" x="1" y="1" width="571" height="122" frameX="-28" frameY="-10" frameWidth="612" frameHeight="132"/>
	<SubTexture name="mp3 capsule w backing0006" x="1" y="126" width="571" height="122" frameX="-28" frameY="-10" frameWidth="612" frameHeight="132"/>
	<SubTexture name="mp3 capsule w backing0007" x="1" y="251" width="564" height="124" frameX="-35" frameY="-8" frameWidth="612" frameHeight="132"/>
	<SubTexture name="mp3 capsule w backing0008" x="1" y="378" width="564" height="124" frameX="-35" frameY="-8" frameWidth="612" frameHeight="132"/>
</TextureAtlas>