{
  "version": "2.2.4",
  "songName": "Monster",
  "artist": "BassetFilms",
  "charter": "ChaoticGamerCG + MtH + Spazkid",
  "playData": {
    "difficulties": ["easy", "normal", "hard"],
    "characters": { "player": "bf", "girlfriend": "gf", "opponent": "monster" },
    "stage": "spookyMansion",
    "noteStyle": "funkin",
    "ratings": { "easy": 1, "normal": 2, "hard": 2 },
    "album": "volume2",
    "previewStart": 0,
    "previewEnd": 15000
  },
  "generatedBy": "Chart Editor Import (FNF Legacy)",
  "timeFormat": "ms",
  "timeChanges": [
    { "t": 0, "bpm": 95 },
    { "t": 35325, "bpm": 127 },
    { "t": 37252, "bpm": 95 },
    { "t": 39789, "bpm": 127 },
    { "t": 41693, "bpm": 100 },
    { "t": 44100, "bpm": 105 },
    { "t": 80571, "bpm": 216 },
    { "t": 81806, "bpm": 95 },
    { "t": 117158, "bpm": 132 },
    { "t": 131705, "bpm": 120 }
  ]
}

