{
	"version": "1.0.0",
	"offsets": [
		-40,
		-135
	],
	"renderType": "sparrow",
	"danceEvery": 1,
	"scale": 1,
	"name": "Otis (Speaker Shooter)",
	"cameraOffsets": [
		0,
		0
	],
	"flipX": false,
	"singTime": 4,
	"startingAnimation": "idle",
	"isPixel": false,
	"assetPath": "characters/otisSpeaker",
	"healthIcon": {
		"offsets": [
			0,
			0
		],
		"id": "otis-speaker",
		"flipX": false,
		"isPixel": false,
		"scale": 1
	},
	"animations": [
		{
			"flipY": false,
			"offsets": [
				0,
				0
			],
			"frameRate": 24,
			"prefix": "otis idle0",
			"flipX": false,
			"looped": false,
			"name": "idle"
		},
		{
			"flipY": false,
			"offsets": [
				-2,
				13
			],
			"frameRate": 24,
			"prefix": "shoot back0",
			"flipX": false,
			"looped": false,
			"name": "shoot1"
		},
		{
			"flipY": false,
			"offsets": [
				-40,
				21
			],
			"frameRate": 24,
			"prefix": "shoot back low0",
			"flipX": false,
			"looped": false,
			"name": "shoot2"
		},
		{
			"flipY": false,
			"offsets": [
				238,
				97
			],
			"frameRate": 24,
			"prefix": "shoot forward0",
			"flipX": false,
			"looped": false,
			"name": "shoot3"
		},
		{
			"flipY": false,
			"offsets": [
				263,
				23
			],
			"frameRate": 24,
			"prefix": "shoot forward low0",
			"flipX": false,
			"looped": false,
			"name": "shoot4"
		}
	]
}