{
	"version": "1.0.0",
	"renderType": "multisparrow",
	"offsets": [
		0,
		-50
	],
	"danceEvery": 1,
	"scale": 1,
	"name": "Tankman",
	"flipX": true,
	"cameraOffsets": [
		0,
		0
	],
	"singTime": 8,
	"startingAnimation": "idle",
	"isPixel": false,
	"assetPath": "characters/tankmanCaptain",
	"healthIcon": {
		"isPixel": false,
		"offsets": [
			0,
			0
		],
		"scale": 1,
		"id": "tankman",
		"flipX": false
	},
	"animations": [
		{
			"offsets": [
				0,
				0
			],
			"flipY": false,
			"frameRate": 24,
			"prefix": "Tankman Idle Dance instance 1",
			"looped": false,
			"name": "idle",
			"flipX": false
		},
		{
			"offsets": [
				92,
				-13
			],
			"flipY": false,
			"frameRate": 24,
			"prefix": "Tankman Right Note instance 1",
			"looped": false,
			"name": "singLEFT",
			"flipX": false
		},
		{
			"offsets": [
				58,
				-104
			],
			"flipY": false,
			"frameRate": 24,
			"prefix": "Tankman DOWN note instance 1",
			"looped": false,
			"name": "singDOWN",
			"flipX": false
		},
		{
			"offsets": [
				55,
				49
			],
			"flipY": false,
			"frameRate": 24,
			"prefix": "Tankman UP note instance 1",
			"looped": false,
			"name": "singUP",
			"flipX": false
		},
		{
			"offsets": [
				-21,
				-31
			],
			"flipY": false,
			"frameRate": 24,
			"prefix": "Tankman Note Left instance 1",
			"looped": false,
			"name": "singRIGHT",
			"flipX": false
		},
		{
			"offsets": [
				-15,
				-9
			],
			"flipY": false,
			"frameRate": 24,
			"prefix": "TANKMAN UGH instance 1",
			"looped": false,
			"name": "ugh",
			"flipX": false
		},
		{
			"offsets": [
				2,
				16
			],
			"flipY": false,
			"frameRate": 24,
			"prefix": "PRETTY GOOD tankman instance 1",
			"looped": false,
			"name": "hehPrettyGood",
			"flipX": false
		},
		{
			"offsets": [
				52,
				1
			],
			"flipY": false,
			"assetPath": "characters/tankmanPico",
			"frameRate": 24,
			"prefix": "tankman ARGH",
			"looped": false,
			"name": "augh",
			"flipX": true
		},
		{
			"offsets": [
				-26,
				12
			],
			"flipY": false,
			"assetPath": "characters/tankmanPico",
			"frameRate": 24,
			"prefix": "tankman laugh",
			"looped": false,
			"name": "laugh",
			"flipX": true
		},
		{
			"offsets": [
				86,
				-15
			],
			"flipY": false,
			"assetPath": "characters/tankmanPico",
			"frameRate": 24,
			"prefix": "tankman beat it",
			"looped": false,
			"name": "beat it",
			"flipX": true
		}
	]
}