<?xml version="1.0" encoding="UTF-8"?>
<!--
Created with Funkin Packer v0.1.3 https://neeeoo.github.io/funkin-packer/
-->
<TextureAtlas imagePath="options.png" width="489" height="957" spritePadding="3" borderPadding="1">
	<SubTexture name="options basic0001" x="1" y="614" width="487" height="112" frameX="0" frameY="0" frameWidth="487" frameHeight="112"/>
	<SubTexture name="options basic0002" x="1" y="614" width="487" height="112" frameX="0" frameY="0" frameWidth="487" frameHeight="112"/>
	<SubTexture name="options basic0003" x="1" y="614" width="487" height="112" frameX="0" frameY="0" frameWidth="487" frameHeight="112"/>
	<SubTexture name="options basic0004" x="1" y="729" width="487" height="112" frameX="0" frameY="0" frameWidth="487" frameHeight="112"/>
	<SubTexture name="options basic0005" x="1" y="729" width="487" height="112" frameX="0" frameY="0" frameWidth="487" frameHeight="112"/>
	<SubTexture name="options basic0006" x="1" y="729" width="487" height="112" frameX="0" frameY="0" frameWidth="487" frameHeight="112"/>
	<SubTexture name="options basic0007" x="1" y="844" width="487" height="112" frameX="0" frameY="0" frameWidth="487" frameHeight="112"/>
	<SubTexture name="options basic0008" x="1" y="844" width="487" height="112" frameX="0" frameY="0" frameWidth="487" frameHeight="112"/>
	<SubTexture name="options basic0009" x="1" y="844" width="487" height="112" frameX="0" frameY="0" frameWidth="487" frameHeight="112"/>
	<SubTexture name="options white0001" x="331" y="1" width="157" height="608" rotated="true" frameX="-1" frameY="0" frameWidth="610" frameHeight="164"/>
	<SubTexture name="options white0002" x="168" y="1" width="160" height="608" rotated="true" frameX="-2" frameY="0" frameWidth="610" frameHeight="164"/>
	<SubTexture name="options white0003" x="1" y="1" width="164" height="610" rotated="true" frameX="0" frameY="0" frameWidth="610" frameHeight="164"/>
</TextureAtlas>