{
  "version": "1.0",
  "name": "Limo Ride",
  "cameraZoom": 0.9,
  "props": [
    {
      "name": "limoSunset",
      "assetPath": "limo/limoSunset",
      "position": [-120, -50],
      "scale": [1, 1],
      "scroll": [0.1, 0.1],
      "zIndex": 10
    },
    {
      "name": "bgLimo",
      "assetPath": "limo/bgLimo",
      "position": [-200, 480],
      "scale": [1, 1],
      "scroll": [0.4, 0.4],
      "zIndex": 20,
      "animations": [
        {
          "name": "drive",
          "prefix": "background limo pink",
          "frameRate": 24,
          "loop": true,
          "flipX": false,
          "flipY": false
        }
      ],
      "startingAnimation": "drive"
    },
    {
      "name": "limo",
      "assetPath": "limo/limoDrive",
      "position": [-120, 550],
      "scale": [1, 1],
      "scroll": [1, 1],
      "zIndex": 150,
      "animations": [
        {
          "name": "drive",
          "prefix": "Limo stage",
          "frameRate": 24,
          "loop": true,
          "flipX": false,
          "flipY": false
        }
      ],
      "startingAnimation": "drive"
    },
    {
      "name": "fastCar",
      "assetPath": "limo/fastCarLol",
      "position": [-12600, 160],
      "scale": [1, 1],
      "scroll": [1, 1],
      "zIndex": 90
    },

    {
      "name": "limoDancer1",
      "assetPath": "limo/limoDancer",
      "position": [500, 80],
      "scale": [1, 1],
      "scroll": [0.4, 0.4],
      "zIndex": 30,
      "danceEvery": 1,
      "startingAnimation": "danceLeft",
      "animations": [
        {
          "name": "danceLeft",
          "prefix": "bg dancer sketch PINK",
          "frameRate": 24,
          "frameIndices": [0, 1, 2, 3, 4, 5, 6, 7, 8, 9, 10, 11, 12, 13, 14],
          "loop": false,
          "flipX": false,
          "flipY": false
        },
        {
          "name": "danceRight",
          "prefix": "bg dancer sketch PINK",
          "frameRate": 24,
          "frameIndices": [
            15, 16, 17, 18, 19, 20, 21, 22, 23, 24, 25, 26, 27, 28, 29
          ],
          "loop": false,
          "flipX": false,
          "flipY": false
        }
      ]
    },

    {
      "name": "limoDancer2",
      "assetPath": "limo/limoDancer",
      "position": [870, 80],
      "scale": [1, 1],
      "scroll": [0.4, 0.4],
      "zIndex": 30,
      "danceEvery": 1,
      "startingAnimation": "danceLeft",
      "animations": [
        {
          "name": "danceLeft",
          "prefix": "bg dancer sketch PINK",
          "frameRate": 24,
          "frameIndices": [0, 1, 2, 3, 4, 5, 6, 7, 8, 9, 10, 11, 12, 13, 14],
          "loop": false,
          "flipX": false,
          "flipY": false
        },
        {
          "name": "danceRight",
          "prefix": "bg dancer sketch PINK",
          "frameRate": 24,
          "frameIndices": [
            15, 16, 17, 18, 19, 20, 21, 22, 23, 24, 25, 26, 27, 28, 29
          ],
          "loop": false,
          "flipX": false,
          "flipY": false
        }
      ]
    },

    {
      "name": "limoDancer3",
      "assetPath": "limo/limoDancer",
      "position": [1240, 80],
      "scale": [1, 1],
      "scroll": [0.4, 0.4],
      "zIndex": 30,
      "danceEvery": 1,
      "startingAnimation": "danceLeft",
      "animations": [
        {
          "name": "danceLeft",
          "prefix": "bg dancer sketch PINK",
          "frameRate": 24,
          "frameIndices": [0, 1, 2, 3, 4, 5, 6, 7, 8, 9, 10, 11, 12, 13, 14],
          "loop": false,
          "flipX": false,
          "flipY": false
        },
        {
          "name": "danceRight",
          "prefix": "bg dancer sketch PINK",
          "frameRate": 24,
          "frameIndices": [
            15, 16, 17, 18, 19, 20, 21, 22, 23, 24, 25, 26, 27, 28, 29
          ],
          "loop": false,
          "flipX": false,
          "flipY": false
        }
      ]
    },

    {
      "name": "limoDancer4",
      "assetPath": "limo/limoDancer",
      "position": [1610, 80],
      "scale": [1, 1],
      "scroll": [0.4, 0.4],
      "zIndex": 30,
      "danceEvery": 1,
      "startingAnimation": "danceLeft",
      "animations": [
        {
          "name": "danceLeft",
          "prefix": "bg dancer sketch PINK",
          "frameRate": 24,
          "frameIndices": [0, 1, 2, 3, 4, 5, 6, 7, 8, 9, 10, 11, 12, 13, 14],
          "loop": false,
          "flipX": false,
          "flipY": false
        },
        {
          "name": "danceRight",
          "prefix": "bg dancer sketch PINK",
          "frameRate": 24,
          "frameIndices": [
            15, 16, 17, 18, 19, 20, 21, 22, 23, 24, 25, 26, 27, 28, 29
          ],
          "loop": false,
          "flipX": false,
          "flipY": false
        }
      ]
    },

    {
      "name": "limoDancer5",
      "assetPath": "limo/limoDancer",
      "position": [1980, 80],
      "scale": [1, 1],
      "scroll": [0.4, 0.4],
      "zIndex": 30,
      "danceEvery": 1,
      "startingAnimation": "danceLeft",
      "animations": [
        {
          "name": "danceLeft",
          "prefix": "bg dancer sketch PINK",
          "frameRate": 24,
          "frameIndices": [0, 1, 2, 3, 4, 5, 6, 7, 8, 9, 10, 11, 12, 13, 14],
          "loop": false,
          "flipX": false,
          "flipY": false
        },
        {
          "name": "danceRight",
          "prefix": "bg dancer sketch PINK",
          "frameRate": 24,
          "frameIndices": [
            15, 16, 17, 18, 19, 20, 21, 22, 23, 24, 25, 26, 27, 28, 29
          ],
          "loop": false,
          "flipX": false,
          "flipY": false
        }
      ]
    }
  ],
  "characters": {
    "bf": {
      "zIndex": 300,
      "position": [550, 710]
    },
    "gf": { "zIndex": 100, "position": [400, 130] },
    "dad": { "zIndex": 200, "position": [100, 100] }
  }
}
